readme_update-0.3.0.dist-info/METADATA
readme_update-0.3.0.dist-info/WHEEL
readme_update/__init__.py
readme_update/readme_update.cpython-313-darwin.so
update_readme/__init__.py
update_readme/__main__.py
readme_update-0.3.0.dist-info/RECORD
