Metadata-Version: 2.4
Name: readme-update
Version: 0.3.0
Classifier: Programming Language :: Rust
Classifier: Programming Language :: Python :: Implementation :: CPython
Classifier: Programming Language :: Python :: Implementation :: PyPy
License: MIT
Requires-Python: >=3.10
